[{"id":"e6450cd2.f3531","type":"exec","z":"d559d29e.83b94","command":"python home/pi/fitbit_python/fitbit_run.py","addpay":true,"append":"","useSpawn":"","timer":"","name":"Fitbit Python","x":82,"y":149.5,"wires":[["56285428.b77ddc","4cead7be.22d1f8"],[],[]]},{"id":"6bcd742d.4c291c","type":"debug","z":"d559d29e.83b94","name":"","active":true,"console":"false","complete":"false","x":653,"y":197,"wires":[]},{"id":"6027f85a.4063d8","type":"function","z":"d559d29e.83b94","name":"assemble query","func":"\nmsg.topic = \"INSERT INTO cardio \\\n(run_time, start_distance, start_steps) \\\nVALUES (\" + msg.payload.date + \", \" + msg.payload.distance + \",\" + \nmsg.payload.steps + \")\"\n\nreturn msg;","outputs":1,"noerr":0,"x":341,"y":199,"wires":[["bcdb3018.d5ee9"]]},{"id":"4cead7be.22d1f8","type":"json","z":"d559d29e.83b94","name":"","x":192,"y":238,"wires":[["6027f85a.4063d8"]]},{"id":"bcdb3018.d5ee9","type":"mysql","z":"d559d29e.83b94","mydb":"bcab100e.cd8a6","name":"Access Pi Storage","x":502.5,"y":138,"wires":[["6bcd742d.4c291c","b5730a3b.ff6098"]]},{"id":"56285428.b77ddc","type":"debug","z":"d559d29e.83b94","name":"","active":true,"console":"false","complete":"false","x":295.5,"y":84,"wires":[]},{"id":"b5730a3b.ff6098","type":"template","z":"d559d29e.83b94","name":"Alexa Response","field":"payload","fieldType":"msg","format":"handlebars","syntax":"mustache","template":"Started cardio, have fun!","x":708.5,"y":115.5,"wires":[[]]},{"id":"bcab100e.cd8a6","type":"MySQLdatabase","z":"3007504e.faa71","host":"127.0.0.1","port":"3306","db":"alexapi","tz":"UTC"}]